{
    "seed_everything": 5,
    "pre_process": {
        "do": false,
        "col": "",
        "xentropy": false
    },
    "post_process": {
        "params": {},
        "do": false,
        "col": ""
    },
    "stacking": {},
    "dataset": {
        "dir": "input/",
        "feature_dir": "features",
        "params": null
    },
    "feature_engineering": {
        "sampling": {
            "make": {
                "params": {}
            },
            "save": {
                "params": {}
            },
            "train": {
                "params": {}
            }
        }
    },
    "feature_selection": {
        "SpearmanCorrelation": {
            "dryrun": true
        },
        "top_k": {
            "do": true,
            "importance": "034_seed_average_033",
            "top_k": 0.1
        }
    },
    "av": {
        "params": {},
        "split_params": {},
        "model_params": {},
        "train_params": {}
    },
    "model": {
        "name": "xgb",
        "sampling": {
            "name": "none",
            "params": {}
        },
        "adaptive_learning_rate": {},
        "focal_loss": {},
        "model_params": {
            "objective": "reg:squarederror",
            "booster": "gbtree",
            "eval_metric": "rmse",
            "tree_method": "gpu_hist",
            "max_depth": 6,
            "learning_rate": 0.01,
            "n_estimators": 10000,
            "min_child_weight": 1.0,
            "gamma": 0.0,
            "colsample_bytree": 0.7,
            "colsample_bylevel": 0.3,
            "reg_alpha": 0.0,
            "reg_lambda": 1.0,
            "verbosity": 0,
            "seed": 5,
            "random_state": 5
        },
        "train_params": {
            "early_stopping_rounds": 200,
            "verbose": true
        },
        "mode": "regression"
    },
    "val": {
        "name": "stratified_group_kfold",
        "params": {
            "group": "Publisher",
            "target": "group",
            "n_splits": 5,
            "random_state": 5
        },
        "percentile": 95
    },
    "output_dir": "output/042_EU_sales_target_seed_average",
    "features": [
        "Basic",
        "GroupbyPublisher",
        "GroupbyDeveloper",
        "GroupbyPlatform",
        "GroupbyGenre",
        "GroupbyYear",
        "GroupbyRating",
        "CategoryVectorization",
        "ConcatCategory",
        "GroupbyConcatCat"
    ],
    "target": "EU_Sales",
    "target_encoding": false,
    "args": {
        "config": "config/042_EU_sales_target_seed_average/seed_05.yml"
    },
    "model_output_dir": "output/042_EU_sales_target_seed_average/seed_05",
    "categorical_cols": [
        "PlatformPublisher_combi"
    ],
    "eval_results": {
        "evals_result": {
            "oof_score": 1.1314784628208852,
            "cv_score": {
                "cv1": 1.116971,
                "cv2": 0.990458,
                "cv3": 1.306658,
                "cv4": 1.102626,
                "cv5": 1.10901
            },
            "n_data": 8359,
            "best_iteration": 1175.4,
            "n_features": 467,
            "feature_importance": {
                "ratio_min_User_Count_groupby_PlatformGenre_combi": 0.04606166109442711,
                "diff_mean_log_User_Count_groupby_PlatformGenre_combi": 0.031229320913553238,
                "diff_min_User_Count_groupby_Platform": 0.021391112357378006,
                "diff_mean_log_User_Count_groupby_Platform": 0.02121996134519577,
                "diff_std_log_User_Count_groupby_Platform": 0.020181817933917046,
                "ratio_max_log_User_Count_groupby_Rating": 0.018965307623147964,
                "std_log_User_Count_groupby_Publisher": 0.016351964324712753,
                "diff_min_log_User_Count_groupby_GenrePublisher_combi": 0.0139872832223773,
                "ratio_mean_User_Count_groupby_GenreRating_combi": 0.013935508206486702,
                "ratio_max_User_Count_groupby_Rating": 0.012552988715469837,
                "count_publisher_168_0_groupby_platform": 0.011080090887844563,
                "count_publisher_349_0_groupby_platform": 0.009572123177349567,
                "CountLDA20_Publisher_Platform_13": 0.008998649194836617,
                "count_year_of_release_2010_0_groupby_publisher": 0.008709878660738468,
                "mean_User_Count_groupby_NamePlatform_combi": 0.008334772661328316,
                "count_genre_9_0_groupby_publisher": 0.007632148452103138,
                "CountLDA20_Publisher_Platform_5": 0.00719253858551383,
                "count_publisher_325_0_groupby_platform": 0.007143800146877766,
                "CountLDA20_Publisher_Platform_19": 0.006969475653022528,
                "CountLDA30_Name_Platform_29": 0.006377698387950659,
                "CountLDA30_Name_Publisher_7": 0.006303821690380573,
                "CountLDA30_Publisher_Platform_26": 0.00585315003991127,
                "mean_log_User_Count_groupby_Platform": 0.005701083689928055,
                "nunique_Developer_groupby_Publisher": 0.005328229162842035,
                "CountLDA10_Publisher_Name_2": 0.005261728074401617,
                "CountLDA30_Name_Publisher_6": 0.005218361970037222,
                "ratio_mean_User_Count_groupby_Platform": 0.005212841089814901,
                "sum_Critic_Count_groupby_Publisher": 0.005180376581847668,
                "CountLDA20_Publisher_Platform_17": 0.005115480162203312,
                "count_publisher_28_0_groupby_platform": 0.004951220005750656,
                "ratio_std_log_User_Count_groupby_Genre": 0.004839979112148285,
                "diff_mean_log_User_Count_groupby_PlatformPublisher_combi": 0.004688820336014032,
                "CountLDA30_Name_Platform_11": 0.004614565055817366,
                "sum_Critic_Count_groupby_GenrePublisher_combi": 0.004427168518304825,
                "CountLDA30_Name_Publisher_21": 0.004244721960276365,
                "count_genre_4_0_groupby_publisher": 0.004178387112915516,
                "count_platform_3_groupby_publisher": 0.004156388808041811,
                "min_User_Score_groupby_Platform": 0.00413545174524188,
                "count_publisher_5_0_groupby_platform": 0.004036093130707741,
                "CountLDA30_Publisher_Genre_8": 0.004012429155409336,
                "count_publisher_436_0_groupby_platform": 0.0039987713098526,
                "CountLDA30_Name_Publisher_13": 0.003969750367105007,
                "count_publisher_433_0_groupby_year": 0.0038868230767548084,
                "log_User_Count": 0.0038828670512884855,
                "max_Critic_Count_groupby_PublisherDeveloper_combi": 0.0038627423346042633,
                "nunique_PlatformGenre_combi_groupby_PublisherDeveloper_combi": 0.003788870992138982,
                "CountLDA30_Developer_Rating_10": 0.0037399684078991413,
                "count_year_of_release_2006_0_groupby_publisher": 0.0037251811008900404,
                "count_publisher_51_0_groupby_platform": 0.0036893263459205627,
                "nunique_Rating_groupby_Platform": 0.0036819532979279757,
                "CountLDA10_Platform_Publisher_9": 0.0035905838012695312,
                "min_User_Score_groupby_Publisher": 0.0034499652683734894,
                "diff_Year_of_Release_groupby_Genre": 0.0033843989949673414,
                "CountLDA10_Publisher_Developer_8": 0.0033780881203711033,
                "CountLDA20_Publisher_Developer_6": 0.003364423755556345,
                "count_publisher_120_0_groupby_platform": 0.00335312751121819,
                "count_publisher_292_0_groupby_platform": 0.003344489261507988,
                "count_platform_10_groupby_genre": 0.0032825942616909742,
                "CountLDA30_Publisher_Developer_0": 0.0032518492080271244,
                "std_User_Score_groupby_Publisher": 0.00323965260758996,
                "diff_mean_User_Count_groupby_Platform": 0.0032066944986581802,
                "count_year_of_release_2016_0_groupby_publisher": 0.0032037696801126003,
                "count_platform_16_groupby_publisher": 0.003151466604322195,
                "count_publisher_569_0_groupby_year": 0.003141542198136449,
                "ratio_std_User_Count_groupby_Platform": 0.0031241360120475292,
                "CountLDA20_Platform_Rating_4": 0.0029882199596613646,
                "CountLDA10_Name_Publisher_5": 0.0029880539514124393,
                "mean_User_Count_groupby_Publisher": 0.00293459789827466,
                "count_publisher_207_0_groupby_genre": 0.0029264292679727077,
                "count_publisher_348_0_groupby_genre": 0.002920355647802353,
                "min_Year_of_Release_groupby_Platform": 0.002888163086026907,
                "CountLDA20_Platform_Name_13": 0.0028721268754452467,
                "CountLDA30_Name_Platform_2": 0.002847745781764388,
                "count_publisher_314_0_groupby_platform": 0.0028271398041397333,
                "CountLDA30_Publisher_Genre_21": 0.0027861222624778748,
                "CountLDA20_Platform_Publisher_19": 0.0027745836414396763,
                "count_publisher_113_0_groupby_year": 0.002742943586781621,
                "min_User_Score_groupby_GenrePublisher_combi": 0.002721650991588831,
                "CountLDA30_Platform_Developer_24": 0.002638135338202119,
                "count_rating_1_0_groupby_platform": 0.002600796055048704,
                "count_publisher_140_0_groupby_platform": 0.0025963629595935345,
                "ratio_mean_User_Count_groupby_PlatformGenre_combi": 0.0025951052084565163,
                "CountLDA5_Publisher_Name_4": 0.0025872245896607637,
                "CountLDA20_Publisher_Genre_9": 0.0025626844726502895,
                "count_year_of_release_1992_0_groupby_platform": 0.0025612511672079563,
                "CountLDA5_Platform_Publisher_3": 0.0025513828732073307,
                "CountLDA5_Platform_Genre_2": 0.0025506436359137297,
                "ratio_min_log_User_Count_groupby_Year_of_Release": 0.002544210758060217,
                "count_year_of_release_2004_0_groupby_platform": 0.0025276162195950747,
                "CountLDA20_Publisher_Rating_12": 0.002516617067158222,
                "CountLDA30_Name_Rating_22": 0.0025150387082248926,
                "count_genre_5_0_groupby_platform": 0.0025139241479337215,
                "CountLDA5_Name_Genre_4": 0.002499220659956336,
                "CountLDA20_Name_Publisher_0": 0.0024986774660646915,
                "CountLDA20_Publisher_Name_15": 0.0024884925223886967,
                "sum_Critic_Count_groupby_NamePlatform_combi": 0.0024510992225259542,
                "CountLDA30_Platform_Name_20": 0.00243382528424263,
                "count_publisher_341_0_groupby_genre": 0.0024289735592901707,
                "diff_mean_Critic_Count_groupby_Platform": 0.002415472874417901,
                "count_publisher_410_0_groupby_genre": 0.0023991744965314865,
                "CountLDA30_Platform_Genre_17": 0.002386774867773056,
                "CountLDA20_Name_Publisher_12": 0.002382589504122734,
                "diff_count_PlatformDeveloper_combi_groupby_DeveloperRating_combi": 0.0023801953066140413,
                "CountLDA20_Platform_Genre_7": 0.002348619047552347,
                "count_year_of_release_2010_0_groupby_genre": 0.0023466632701456547,
                "CountLDA20_Name_Platform_8": 0.002328338101506233,
                "ratio_max_User_Count_groupby_Genre": 0.0023089007008820772,
                "count_publisher_435_0_groupby_platform": 0.0023029414005577564,
                "count_publisher_203_0_groupby_genre": 0.0023009926080703735,
                "CountLDA10_Publisher_Platform_4": 0.002274279249832034,
                "CountLDA20_Publisher_Developer_4": 0.0022569471038877964,
                "count_publisher_489_0_groupby_platform": 0.0022540234494954348,
                "diff_std_log_User_Count_groupby_Developer": 0.002241435693576932,
                "min_Critic_Count_groupby_NamePlatform_combi": 0.002185963559895754,
                "CountLDA30_Name_Rating_15": 0.0021634711883962154,
                "CountLDA10_Publisher_Rating_7": 0.0021408996544778347,
                "CountLDA20_Publisher_Developer_9": 0.0021137166768312454,
                "count_publisher_568_0_groupby_year": 0.0020974588114768267,
                "CountLDA5_Publisher_Name_2": 0.0020918434020131826,
                "CountLDA20_Publisher_Platform_16": 0.0020604878664016724,
                "nunique_Developer_groupby_Year_of_Release": 0.002051692456007004,
                "diff_min_User_Count_groupby_Year_of_Release": 0.002036679070442915,
                "count_publisher_314_0_groupby_year": 0.002032185671851039,
                "count_publisher_87_0_groupby_rating": 0.0020313377026468515,
                "count_publisher_459_0_groupby_year": 0.002028905088081956,
                "CountLDA10_Platform_Genre_1": 0.00202786922454834,
                "ratio_nunique_PlatformPublisher_combi_groupby_DeveloperRating_combi": 0.0020082227420061827,
                "min_Critic_Score_groupby_Genre": 0.0019828961230814457,
                "count_publisher_360_0_groupby_year": 0.0019779051654040813,
                "count_publisher_374_0_groupby_platform": 0.001976345432922244,
                "count_publisher_474_0_groupby_platform": 0.0019725740421563387,
                "CountLDA30_Platform_Developer_21": 0.001971013844013214,
                "CountLDA20_Name_Publisher_3": 0.0019700885750353336,
                "count_publisher_42_0_groupby_year": 0.0019585429690778255,
                "count_year_of_release_2015_0_groupby_publisher": 0.0019569466821849346,
                "CountLDA20_Name_Rating_5": 0.0019544826354831457,
                "count_publisher_487_0_groupby_genre": 0.0019296755781397223,
                "CountLDA30_Platform_Publisher_17": 0.0019264159491285682,
                "Year_of_Release": 0.0019192311447113752,
                "diff_mean_Critic_Count_groupby_Rating": 0.0019154560286551714,
                "count_publisher_323_0_groupby_year": 0.0019150178413838148,
                "ratio_count_PublisherDeveloper_combi_groupby_DeveloperRating_combi": 0.0019074513111263514,
                "diff_count_Rating_groupby_DeveloperRating_combi": 0.001883198507130146,
                "ratio_count_PlatformGenre_combi_groupby_DeveloperRating_combi": 0.0018753714393824339,
                "ratio_nunique_PlatformGenre_combi_groupby_PlatformDeveloper_combi": 0.0018747685244306922,
                "mean_User_Score_groupby_Genre": 0.001860808813944459,
                "count_publisher_422_0_groupby_genre": 0.001836013630963862,
                "mean_Critic_Score_groupby_Publisher": 0.0018229002598673105,
                "sum_log_User_Count_groupby_Publisher": 0.001809053821489215,
                "diff_count_PublisherDeveloper_combi_groupby_DeveloperRating_combi": 0.0018085797782987356,
                "count_publisher_178_0_groupby_year": 0.0018027964979410172,
                "count_publisher_91_0_groupby_platform": 0.0017717952141538262,
                "count_publisher_321_0_groupby_genre": 0.001762619474902749,
                "count_publisher_504_0_groupby_year": 0.001762556261382997,
                "count_publisher_362_0_groupby_year": 0.0017583215376362205,
                "count_publisher_439_0_groupby_genre": 0.0017499607056379318,
                "diff_count_Publisher_groupby_GenrePublisher_combi": 0.0017414640169590712,
                "ratio_count_Platform_groupby_Rating": 0.0017379174241796136,
                "std_log_User_Count_groupby_Platform": 0.0017237223219126463,
                "CountLDA10_Developer_Rating_8": 0.0017207857454195619,
                "count_platform_21_groupby_year": 0.0017199779395014048,
                "CountLDA20_Platform_Genre_15": 0.0017177145928144455,
                "diff_std_User_Count_groupby_Rating": 0.001708734082058072,
                "max_Critic_Count_groupby_NamePlatform_combi": 0.0016950119752436876,
                "ratio_count_Name_groupby_Year_of_Release": 0.0016899777110666037,
                "count_year_of_release_2011_0_groupby_genre": 0.0016727723414078355,
                "count_publisher_567_0_groupby_rating": 0.0016600979724898934,
                "CountLDA30_Name_Rating_13": 0.0016554569592699409,
                "CountLDA20_Publisher_Developer_10": 0.0016545895487070084,
                "CountLDA5_Publisher_Developer_1": 0.001652025617659092,
                "max_Critic_Score_groupby_GenrePublisher_combi": 0.001648005098104477,
                "CountLDA20_Genre_Platform_14": 0.0016464407090097666,
                "count_publisher_64_0_groupby_rating": 0.0016407081857323647,
                "diff_sum_log_User_Count_groupby_PlatformPublisher_combi": 0.0016361235175281763,
                "diff_min_Critic_Count_groupby_PlatformGenre_combi": 0.001628788886591792,
                "count_publisher_79_0_groupby_genre": 0.0016214862698689103,
                "CountLDA20_Developer_Publisher_14": 0.0016164906555786729,
                "count_publisher_268_0_groupby_genre": 0.0016034368891268969,
                "count_year_of_release_1998_0_groupby_publisher": 0.001597437309101224,
                "count_publisher_22_0_groupby_year": 0.0015939753502607346,
                "count_publisher_361_0_groupby_genre": 0.0015923226019367576,
                "count_publisher_328_0_groupby_genre": 0.0015875145327299833,
                "ratio_nunique_Name_groupby_PublisherDeveloper_combi": 0.0015825096052139997,
                "diff_nunique_PlatformPublisher_combi_groupby_GenreDeveloper_combi": 0.001575756585225463,
                "CountLDA30_Platform_Publisher_0": 0.0015713784378021955,
                "CountLDA30_Developer_Platform_13": 0.0015528392978012562,
                "count_publisher_44_0_groupby_genre": 0.001552608679048717,
                "PlatformPublisher_combi": 0.0015402266290038824,
                "count_Developer_groupby_DeveloperRating_combi": 0.0015219658380374312,
                "max_User_Count_groupby_PlatformGenre_combi": 0.0015175302978605032,
                "count_genre_2_0_groupby_platform": 0.0015148090897127986,
                "diff_sum_Year_of_Release_groupby_Platform": 0.0015124803176149726,
                "max_User_Count_groupby_NamePlatform_combi": 0.0015118794981390238,
                "ratio_count_Rating_groupby_GenrePublisher_combi": 0.0015007040929049253,
                "count_publisher_566_0_groupby_year": 0.0014889450976625085,
                "count_publisher_260_0_groupby_genre": 0.0014887336874380708,
                "count_publisher_370_0_groupby_genre": 0.0014861688250675797,
                "count_publisher_332_0_groupby_platform": 0.0014829417923465371,
                "count_publisher_7_0_groupby_platform": 0.0014826258411630988,
                "count_publisher_8_0_groupby_genre": 0.001477819518186152,
                "count_publisher_109_0_groupby_genre": 0.0014752302085980773,
                "CountLDA5_Genre_Platform_3": 0.0014731065602973104,
                "count_platform_17_groupby_genre": 0.0014713348355144262,
                "diff_std_log_User_Count_groupby_DeveloperRating_combi": 0.0014707049122080207,
                "CountLDA20_Publisher_Developer_14": 0.0014696952421218157,
                "count_publisher_450_0_groupby_genre": 0.0014529991894960403,
                "count_publisher_570_0_groupby_platform": 0.00144172552973032,
                "CountLDA30_Developer_Rating_12": 0.0014259067829698324,
                "max_User_Count_groupby_PublisherDeveloper_combi": 0.0014210843946784735,
                "count_Name_groupby_GenrePublisher_combi": 0.001412742305546999,
                "ratio_count_Rating_groupby_Platform": 0.0013990284642204642,
                "diff_count_Rating_groupby_PublisherDeveloper_combi": 0.0013964090030640364,
                "count_year_of_release_1998_0_groupby_genre": 0.001391175203025341,
                "CountLDA10_Developer_Rating_2": 0.0013898748438805342,
                "CountLDA30_Publisher_Name_2": 0.0013796836137771606,
                "CountLDA20_Name_Rating_11": 0.001379170804284513,
                "count_publisher_124_0_groupby_genre": 0.0013779711443930864,
                "diff_std_User_Score_groupby_DeveloperRating_combi": 0.0013764594914391637,
                "count_publisher_307_0_groupby_genre": 0.0013673810753971338,
                "count_publisher_457_0_groupby_rating": 0.0013600183883681893,
                "count_year_of_release_1996_0_groupby_genre": 0.0013589819427579641,
                "CountLDA30_Name_Platform_17": 0.0013511879369616508,
                "ratio_count_GenrePublisher_combi_groupby_PublisherDeveloper_combi": 0.0013511519646272063,
                "diff_min_User_Score_groupby_Publisher": 0.0013485429808497429,
                "diff_min_User_Count_groupby_PlatformDeveloper_combi": 0.0013484325027093291,
                "count_publisher_30_0_groupby_rating": 0.0013345088809728622,
                "count_publisher_258_0_groupby_platform": 0.0013294726377353072,
                "CountLDA30_Developer_Name_20": 0.0013294524978846312,
                "diff_sum_Critic_Score_groupby_Year_of_Release": 0.001320075592957437,
                "diff_max_log_User_Count_groupby_Publisher": 0.0013037618482485414,
                "count_publisher_55_0_groupby_platform": 0.001298178220167756,
                "count_publisher_322_0_groupby_year": 0.0012937859864905477,
                "diff_sum_log_User_Count_groupby_Rating": 0.0012921871384605765,
                "nunique_Rating_groupby_Publisher": 0.0012885716278105974,
                "diff_nunique_Genre_groupby_PlatformDeveloper_combi": 0.0012882177252322435,
                "ratio_nunique_PlatformGenre_combi_groupby_DeveloperRating_combi": 0.0012809369945898652,
                "CountLDA30_Genre_Platform_18": 0.0012807289604097605,
                "count_publisher_553_0_groupby_platform": 0.0012777270749211311,
                "ratio_count_PlatformGenre_combi_groupby_GenrePublisher_combi": 0.001269444008357823,
                "CountLDA30_Publisher_Name_5": 0.0012692672898992896,
                "count_publisher_403_0_groupby_year": 0.0012543996563181281,
                "count_publisher_44_0_groupby_rating": 0.0012534306151792407,
                "count_rating_5_0_groupby_year": 0.001244274666532874,
                "CountLDA30_Rating_Name_25": 0.0012408829061314464,
                "count_publisher_447_0_groupby_rating": 0.0012284949189051986,
                "count_publisher_176_0_groupby_platform": 0.0012272800086066127,
                "count_publisher_449_0_groupby_platform": 0.0012152653653174639,
                "count_publisher_535_0_groupby_genre": 0.0012099217856302857,
                "CountLDA30_Name_Developer_12": 0.0012035646941512823,
                "diff_count_Genre_groupby_Developer": 0.0012013291707262397,
                "CountLDA30_Name_Developer_23": 0.001192830502986908,
                "count_publisher_370_0_groupby_year": 0.0011921721743419766,
                "count_publisher_13_0_groupby_year": 0.0011908021988347173,
                "count_year_of_release_1987_0_groupby_publisher": 0.0011903431732207537,
                "ratio_count_Publisher_groupby_Genre": 0.0011896558571606874,
                "count_publisher_495_0_groupby_genre": 0.0011869992595165968,
                "count_publisher_246_0_groupby_year": 0.001186656765639782,
                "ratio_min_Critic_Score_groupby_PlatformPublisher_combi": 0.0011779196793213487,
                "nunique_Publisher_groupby_GenreRating_combi": 0.0011746103409677744,
                "CountLDA20_Rating_Developer_3": 0.0011716826120391488,
                "diff_max_log_User_Count_groupby_Platform": 0.0011688834056258202,
                "CountLDA10_Genre_Developer_1": 0.0011673789704218507,
                "CountLDA30_Developer_Genre_0": 0.0011671053944155574,
                "count_publisher_546_0_groupby_year": 0.0011553902877494693,
                "count_platform_18_groupby_genre": 0.0011532206553965807,
                "CountLDA30_Developer_Name_6": 0.0011486085131764412,
                "CountLDA10_Name_Platform_3": 0.001146909547969699,
                "CountLDA20_Name_Developer_8": 0.0011452084872871637,
                "CountLDA10_Name_Developer_4": 0.0011423627147451043,
                "std_User_Count_groupby_PlatformDeveloper_combi": 0.0011385225225239992,
                "mean_User_Score_groupby_PlatformGenre_combi": 0.0011371937580406666,
                "count_publisher_204_0_groupby_year": 0.0011318189790472388,
                "sum_log_User_Count_groupby_GenreDeveloper_combi": 0.001125702983699739,
                "count_publisher_522_0_groupby_rating": 0.001120830187574029,
                "diff_sum_Critic_Score_groupby_PlatformDeveloper_combi": 0.001113901031203568,
                "count_publisher_474_0_groupby_rating": 0.0011116089299321175,
                "count_publisher_394_0_groupby_year": 0.0011107547907158732,
                "count_publisher_87_0_groupby_platform": 0.001110690413042903,
                "diff_nunique_Developer_groupby_PublisherDeveloper_combi": 0.0011072137858718634,
                "ratio_nunique_Developer_groupby_PlatformDeveloper_combi": 0.0011020819656550884,
                "count_genre_6_0_groupby_Developer": 0.0010970830917358398,
                "CountLDA5_Developer_Platform_3": 0.001095416722819209,
                "count_publisher_254_0_groupby_genre": 0.0010833569103851914,
                "CountLDA20_Developer_Genre_9": 0.001078444067388773,
                "nunique_Name_groupby_GenreRating_combi": 0.0010649490868672729,
                "count_publisher_265_0_groupby_year": 0.0010607352014631033,
                "count_publisher_70_0_groupby_platform": 0.0010586780263110995,
                "count_publisher_296_0_groupby_year": 0.0010584992123767734,
                "count_year_of_release_2010_0_groupby_Developer": 0.0010539389913901687,
                "count_platform_26_groupby_Developer": 0.0010502674849703908,
                "count_publisher_368_0_groupby_genre": 0.0010438772151246667,
                "count_year_of_release_1989_0_groupby_platform": 0.0010428132954984903,
                "std_log_User_Count_groupby_PublisherDeveloper_combi": 0.001038990099914372,
                "ratio_min_log_User_Count_groupby_DeveloperRating_combi": 0.0010375252459198236,
                "CountLDA20_Publisher_Rating_1": 0.0010360253509134054,
                "min_log_User_Count_groupby_PublisherDeveloper_combi": 0.001034432789310813,
                "count_publisher_542_0_groupby_rating": 0.0010260138660669327,
                "ratio_count_Genre_groupby_PlatformDeveloper_combi": 0.0010122801177203655,
                "count_publisher_497_0_groupby_rating": 0.0010113472817465663,
                "count_publisher_442_0_groupby_year": 0.0010085116373375058,
                "count_publisher_371_0_groupby_year": 0.0010035381419584155,
                "diff_nunique_Genre_groupby_Developer": 0.0009979844326153398,
                "CountLDA20_Developer_Platform_9": 0.0009973780252039433,
                "CountLDA5_Rating_Name_1": 0.0009958775481209159,
                "diff_min_Critic_Score_groupby_GenreRating_combi": 0.0009928714716807008,
                "CountLDA10_Publisher_Developer_3": 0.000991301378235221,
                "diff_sum_User_Count_groupby_PlatformDeveloper_combi": 0.0009912285022437572,
                "ratio_nunique_Rating_groupby_PlatformPublisher_combi": 0.0009801744017750025,
                "count_Developer_groupby_PlatformGenre_combi": 0.0009793356293812394,
                "count_Name_groupby_PlatformGenre_combi": 0.0009734147461131215,
                "ratio_mean_Year_of_Release_groupby_Genre": 0.00097251235274598,
                "CountLDA30_Name_Developer_27": 0.0009691574377939105,
                "diff_sum_Critic_Count_groupby_PlatformGenre_combi": 0.0009688910795375705,
                "diff_min_Year_of_Release_groupby_Developer": 0.0009647039696574211,
                "count_publisher_384_0_groupby_year": 0.0009637944167479873,
                "count_publisher_308_0_groupby_rating": 0.000961258658207953,
                "ratio_nunique_DeveloperRating_combi_groupby_PlatformDeveloper_combi": 0.0009602114441804588,
                "count_publisher_441_0_groupby_year": 0.0009554913267493248,
                "ratio_count_Developer_groupby_GenrePublisher_combi": 0.0009524152847006917,
                "ratio_count_Genre_groupby_Rating": 0.0009503312176093459,
                "count_publisher_540_0_groupby_rating": 0.0009466653573326766,
                "diff_min_User_Score_groupby_Genre": 0.000946629501413554,
                "diff_count_Publisher_groupby_Developer": 0.0009425122407265007,
                "ratio_mean_User_Score_groupby_Year_of_Release": 0.0009411488426849246,
                "std_Critic_Count_groupby_Rating": 0.0009396951645612717,
                "diff_max_User_Count_groupby_GenreRating_combi": 0.0009386142482981086,
                "count_platform_11_groupby_publisher": 0.0009380645351484418,
                "count_Name_groupby_GenreRating_combi": 0.0009366391459479928,
                "ratio_max_User_Count_groupby_PlatformPublisher_combi": 0.0009359436808153987,
                "diff_nunique_Developer_groupby_GenrePublisher_combi": 0.0009334927308373153,
                "count_publisher_481_0_groupby_year": 0.0009316508658230305,
                "ratio_min_Year_of_Release_groupby_Genre": 0.0009300859528593719,
                "CountLDA5_Developer_Rating_3": 0.000916759017854929,
                "count_year_of_release_2002_0_groupby_genre": 0.0009143674978986382,
                "count_publisher_501_0_groupby_year": 0.0009019009885378182,
                "min_User_Count_groupby_PlatformDeveloper_combi": 0.0009017343400046229,
                "count_publisher_300_0_groupby_year": 0.000895115896128118,
                "ratio_min_User_Score_groupby_PlatformPublisher_combi": 0.0008905428694561124,
                "diff_std_User_Score_groupby_PlatformDeveloper_combi": 0.0008890858734957874,
                "count_publisher_21_0_groupby_platform": 0.0008872941834852099,
                "min_User_Count_groupby_Developer": 0.0008807342383079231,
                "ratio_min_Critic_Score_groupby_PlatformGenre_combi": 0.0008719200268387794,
                "count_publisher_354_0_groupby_year": 0.0008706633816473186,
                "CountLDA10_Developer_Rating_9": 0.0008660104940645397,
                "ratio_mean_User_Score_groupby_Platform": 0.000862720247823745,
                "diff_nunique_Rating_groupby_Year_of_Release": 0.0008590652723796666,
                "count_publisher_388_0_groupby_year": 0.0008570929057896137,
                "ratio_max_Critic_Score_groupby_Genre": 0.0008546140161342919,
                "CountLDA30_Publisher_Rating_12": 0.0008538966067135334,
                "count_publisher_340_0_groupby_genre": 0.0008533619111403823,
                "diff_min_log_User_Count_groupby_PublisherDeveloper_combi": 0.0008504055440425873,
                "ratio_min_User_Score_groupby_Genre": 0.0008436767384409904,
                "count_Genre_groupby_Rating": 0.0008400846272706985,
                "CountLDA20_Name_Publisher_2": 0.0008394329925067723,
                "count_publisher_298_0_groupby_rating": 0.0008340696804225445,
                "count_publisher_52_0_groupby_year": 0.0008324997616000473,
                "count_publisher_29_0_groupby_platform": 0.0008324336959049106,
                "ratio_mean_User_Score_groupby_PlatformGenre_combi": 0.0008318070322275162,
                "ratio_max_log_User_Count_groupby_DeveloperRating_combi": 0.0008311618003062904,
                "count_publisher_27_0_groupby_platform": 0.0008291527628898621,
                "count_publisher_382_0_groupby_year": 0.0008235780405811965,
                "CountLDA5_Developer_Rating_4": 0.000812831218354404,
                "count_genre_2_0_groupby_Developer": 0.0008106454042717814,
                "CountLDA30_Developer_Genre_1": 0.0008078358368948102,
                "diff_std_User_Score_groupby_Rating": 0.000806536409072578,
                "diff_max_Critic_Score_groupby_PlatformGenre_combi": 0.000801137532107532,
                "count_publisher_63_0_groupby_year": 0.0007898196345195174,
                "ratio_max_log_User_Count_groupby_PlatformDeveloper_combi": 0.0007890220731496811,
                "CountLDA5_Developer_Publisher_2": 0.0007873083231970668,
                "ratio_min_User_Score_groupby_Developer": 0.000781819224357605,
                "count_publisher_169_0_groupby_platform": 0.0007805241039022803,
                "ratio_std_log_User_Count_groupby_PlatformDeveloper_combi": 0.000780111993663013,
                "ratio_std_User_Count_groupby_DeveloperRating_combi": 0.0007741570007055998,
                "diff_nunique_Developer_groupby_PlatformGenre_combi": 0.0007707403274253011,
                "ratio_mean_User_Count_groupby_PlatformPublisher_combi": 0.0007693341467529535,
                "count_publisher_318_0_groupby_year": 0.0007688705809414387,
                "ratio_max_Critic_Count_groupby_PlatformDeveloper_combi": 0.0007643400458618999,
                "count_year_of_release_2007_0_groupby_Developer": 0.0007636136142536998,
                "count_publisher_436_0_groupby_rating": 0.0007608685991726816,
                "count_publisher_28_0_groupby_genre": 0.0007588891312479973,
                "ratio_min_log_User_Count_groupby_PublisherDeveloper_combi": 0.0007587363943457603,
                "ratio_count_Platform_groupby_Developer": 0.000755297252908349,
                "diff_count_Developer_groupby_Genre": 0.0007547507411800325,
                "count_publisher_68_0_groupby_year": 0.0007510890136472881,
                "count_publisher_186_0_groupby_platform": 0.0007498016930185258,
                "count_publisher_499_0_groupby_year": 0.0007490413263440132,
                "sum_log_User_Count_groupby_PlatformGenre_combi": 0.000747624842915684,
                "count_publisher_101_0_groupby_genre": 0.0007468080148100853,
                "count_publisher_422_0_groupby_rating": 0.0007435587467625737,
                "CountLDA10_Rating_Genre_0": 0.0007377454312518239,
                "count_publisher_412_0_groupby_year": 0.0007297958363778889,
                "count_publisher_411_0_groupby_year": 0.0007257401593960822,
                "ratio_min_Year_of_Release_groupby_Developer": 0.0007129083387553692,
                "diff_nunique_Developer_groupby_Genre": 0.0007111012237146497,
                "count_publisher_73_0_groupby_genre": 0.0007072101579979062,
                "CountLDA30_Rating_Platform_16": 0.0006998206372372806,
                "diff_max_Critic_Score_groupby_Developer": 0.0006922883912920952,
                "diff_mean_Critic_Count_groupby_DeveloperRating_combi": 0.0006883418536745012,
                "ratio_std_Critic_Count_groupby_GenreDeveloper_combi": 0.0006872282829135656,
                "count_publisher_488_0_groupby_year": 0.0006857725093141198,
                "diff_max_Critic_Score_groupby_GenrePublisher_combi": 0.0006773550412617624,
                "diff_min_Critic_Score_groupby_PlatformDeveloper_combi": 0.00067519472213462,
                "diff_mean_User_Score_groupby_Developer": 0.0006675220793113112,
                "count_year_of_release_1998_0_groupby_Developer": 0.0006652073352597654,
                "count_publisher_559_0_groupby_year": 0.0006471570231951773,
                "count_publisher_262_0_groupby_year": 0.0006468282081186771,
                "ratio_mean_Critic_Count_groupby_GenreDeveloper_combi": 0.0006462236633524299,
                "count_publisher_495_0_groupby_year": 0.0006448664935305715,
                "count_genre_8_0_groupby_Developer": 0.0006418231641873717,
                "count_publisher_157_0_groupby_platform": 0.0006411903304979205,
                "count_publisher_187_0_groupby_platform": 0.0006405044114217162,
                "diff_max_Critic_Score_groupby_DeveloperRating_combi": 0.0006390564958564937,
                "count_publisher_233_0_groupby_year": 0.0006313581834547222,
                "diff_max_User_Count_groupby_PlatformDeveloper_combi": 0.0006310823955573142,
                "diff_max_Critic_Score_groupby_PublisherDeveloper_combi": 0.0006287394789978862,
                "count_publisher_361_0_groupby_rating": 0.0006246560369618237,
                "count_publisher_319_0_groupby_year": 0.0006192205473780632,
                "CountLDA30_Developer_Publisher_16": 0.0006176657625474036,
                "count_publisher_490_0_groupby_rating": 0.0006084114429540932,
                "count_publisher_436_0_groupby_genre": 0.0006083936896175146,
                "diff_std_Critic_Score_groupby_PlatformDeveloper_combi": 0.0006061930325813591,
                "ratio_min_log_User_Count_groupby_GenreDeveloper_combi": 0.0006052384851500392,
                "CountLDA30_Developer_Rating_8": 0.0006012562662363052,
                "count_publisher_167_0_groupby_year": 0.0006011711666360497,
                "count_publisher_112_0_groupby_rating": 0.0005968935438431799,
                "count_publisher_83_0_groupby_rating": 0.0005872864276170731,
                "diff_mean_Critic_Score_groupby_PublisherDeveloper_combi": 0.0005840779631398618,
                "count_publisher_278_0_groupby_genre": 0.0005801849183626473,
                "count_publisher_189_0_groupby_year": 0.0005800219369120896,
                "count_publisher_149_0_groupby_year": 0.0005686053773388267,
                "count_publisher_83_0_groupby_genre": 0.000564688176382333,
                "diff_max_User_Score_groupby_GenreDeveloper_combi": 0.0005569906788878143,
                "CountLDA20_Platform_Publisher_2": 0.0005548607441596687,
                "count_publisher_281_0_groupby_year": 0.0005548285553231835,
                "ratio_mean_Critic_Score_groupby_Publisher": 0.000544223643373698,
                "count_publisher_420_0_groupby_year": 0.0005425915587693453,
                "count_publisher_238_0_groupby_year": 0.0005399982328526676,
                "diff_nunique_Rating_groupby_NamePlatform_combi": 0.0005396815249696374,
                "count_publisher_257_0_groupby_rating": 0.0005320591735653579,
                "ratio_max_User_Count_groupby_DeveloperRating_combi": 0.0005160732544027269,
                "count_platform_19_groupby_rating": 0.0005157034611329436,
                "count_publisher_405_0_groupby_rating": 0.0005041623371653259,
                "ratio_mean_User_Score_groupby_PlatformPublisher_combi": 0.0005001756944693625,
                "nunique_DeveloperRating_combi_groupby_PublisherDeveloper_combi": 0.0004889525007456541,
                "count_publisher_407_0_groupby_year": 0.0004821076581720263,
                "ratio_max_Critic_Score_groupby_PlatformDeveloper_combi": 0.00047726387856528163,
                "count_publisher_86_0_groupby_rating": 0.0004762972821481526,
                "count_year_of_release_1999_0_groupby_rating": 0.00047340901801362634,
                "count_publisher_2_0_groupby_year": 0.00046924702473916113,
                "count_publisher_185_0_groupby_year": 0.00046700300299562514,
                "count_publisher_339_0_groupby_year": 0.00046418383135460317,
                "count_publisher_235_0_groupby_rating": 0.0004477492184378207,
                "count_publisher_274_0_groupby_year": 0.0003903199394699186,
                "ratio_mean_User_Score_groupby_Developer": 0.00036643765633925796,
                "count_publisher_532_0_groupby_year": 0.0003222416271455586,
                "count_publisher_276_0_groupby_rating": 0.0003080868336837739,
                "count_publisher_552_0_groupby_rating": 0.00027851914637722075,
                "count_publisher_82_0_groupby_rating": 0.0001977664651349187,
                "count_publisher_460_0_groupby_year": 0.0001885814854176715,
                "count_publisher_432_0_groupby_year": 0.00017786036187317222,
                "ratio_max_User_Score_groupby_NamePlatform_combi": 0.00013103237142786384,
                "ratio_std_User_Score_groupby_NamePlatform_combi": 6.334552017506212e-05,
                "diff_max_Critic_Count_groupby_NamePlatform_combi": 4.924495442537591e-06,
                "diff_std_Critic_Score_groupby_NamePlatform_combi": 0.0,
                "diff_std_User_Score_groupby_NamePlatform_combi": 0.0,
                "diff_std_User_Count_groupby_NamePlatform_combi": 0.0,
                "diff_mean_Critic_Score_groupby_NamePlatform_combi": 0.0
            }
        }
    }
}